pyal/__init__.py
pyal/common/__init__.py
pyal/common/algorithm.py
pyal/common/algorithm_TEST.py
pyal/common/logger.py
pyal/graph/__init__.py
pyal/graph/graph.py
pyal/graph/graph_TEST.py
pyal/graph/minimum_span_tree.py
pyal/graph/shortest_path.py
pyal/graph/shortest_path_TEST.py
pyal/graph/topological_traversal.py
pyal/graph/topological_traversal_TEST.py
pyal/list/__init__.py
pyal/list/dequeue.py
pyal/list/dequeue_TEST.py
pyal/list/lfu_cache.py
pyal/list/linked_list.py
pyal/list/linked_list_TEST.py
pyal/list/lru_cache.py
pyal/list/queue.py
pyal/list/queue_TEST.py
pyal/list/stack.py
pyal/list/stack_TEST.py
pyal/string/__init__.py
pyal/string/search.py
pyal/string/search_TEST.py
pyal/tree/__init__.py
pyal/tree/binary_indexed_tree.py
pyal/tree/binary_indexed_tree_TEST.py
pyal/tree/disjoint_set.py
pyal/tree/disjoint_set_TEST.py
pyal/tree/dynamic_heap.py
pyal/tree/dynamic_heap_TEST.py
pyal/tree/max_heap.py
pyal/tree/max_queue.py
pyal/tree/min_heap.py
pyal/tree/min_queue.py
pyal/tree/tree_map.py
pyal/tree/tree_map_TEST.py
python_algorithm_pyal-1.4.2.dist-info/METADATA
python_algorithm_pyal-1.4.2.dist-info/WHEEL
python_algorithm_pyal-1.4.2.dist-info/top_level.txt
python_algorithm_pyal-1.4.2.dist-info/RECORD
