Metadata-Version: 2.4
Name: Python-Algorithm-pyal
Version: 1.4.2
Summary: PYthon Algorithm Library (pyal) targets at providing a python version substitue of STL in C++, such as linked list, tree map, and other data structures and popular algorithms.
Home-page: https://github.com/SummerRainET2008/PYthon_Algorithms_Library
Author-email: tianxia0209@gmail.com
Classifier: Programming Language :: Python :: 3
Classifier: License :: OSI Approved :: MIT License
Classifier: Operating System :: OS Independent
Requires-Python: >=3.8
